snowflake/__init__.py
snowflake/permissions.py
snowflake/version.py
snowflake_native_apps_permission_stub-0.1.11.dist-info/LICENSE.txt
snowflake_native_apps_permission_stub-0.1.11.dist-info/METADATA
snowflake_native_apps_permission_stub-0.1.11.dist-info/WHEEL
snowflake_native_apps_permission_stub-0.1.11.dist-info/top_level.txt
snowflake_native_apps_permission_stub-0.1.11.dist-info/zip-safe
snowflake_native_apps_permission_stub-0.1.11.dist-info/RECORD
